Metadata-Version: 2.1
Name: Orange3-zh
Version: 3.33.1
Summary: Orange, a component-based data mining framework.
Home-page: https://chengxianzn.one/
Author: Bioinformatics Laboratory, FRI UL
Author-email: gengyabc@aliyun.com
License: GPLv3+
Keywords: data mining,machine learning,artificial intelligence
Platform: UNKNOWN
Classifier: Development Status :: 4 - Beta
Classifier: Environment :: X11 Applications :: Qt
Classifier: Environment :: Console
Classifier: Environment :: Plugins
Classifier: Programming Language :: Python
Classifier: License :: OSI Approved :: GNU General Public License v3 or later (GPLv3+)
Classifier: Operating System :: POSIX
Classifier: Operating System :: Microsoft :: Windows
Classifier: Topic :: Scientific/Engineering :: Artificial Intelligence
Classifier: Topic :: Scientific/Engineering :: Visualization
Classifier: Topic :: Software Development :: Libraries :: Python Modules
Classifier: Intended Audience :: Education
Classifier: Intended Audience :: Science/Research
Classifier: Intended Audience :: Developers
License-File: LICENSE
Requires-Dist: AnyQt (>=0.0.13)
Requires-Dist: Pillow (==9.0)
Requires-Dist: baycomp (>=1.0.2)
Requires-Dist: bottleneck (>=1.3.4)
Requires-Dist: chardet (>=3.0.2)
Requires-Dist: dateparser (==1.1.1)
Requires-Dist: httpx (>=0.21.0)
Requires-Dist: joblib (>=0.11)
Requires-Dist: keyring
Requires-Dist: keyrings.alt
Requires-Dist: matplotlib (>=2.2.5)
Requires-Dist: networkx
Requires-Dist: numpy (>=1.17.3)
Requires-Dist: openTSNE (>=0.6.1)
Requires-Dist: openpyxl
Requires-Dist: orange-canvas-core-ml (<0.2a,>=0.1.24)
Requires-Dist: orange-widget-base-ml (>=4.16.1)
Requires-Dist: pandas (>=1.3.0)
Requires-Dist: pip (>=18.0)
Requires-Dist: pygments (>=2.8.0)
Requires-Dist: pyqtgraph (!=0.12.4,>=0.12.2)
Requires-Dist: python-louvain (>=0.13)
Requires-Dist: pyyaml
Requires-Dist: qtconsole (>=4.7.2)
Requires-Dist: requests
Requires-Dist: scikit-learn (>=1.0.1)
Requires-Dist: scipy (!=1.8,>=1.3.1)
Requires-Dist: serverfiles
Requires-Dist: setuptools (>=41.0.0)
Requires-Dist: torch (==1.11.0)
Requires-Dist: torchinfo (==1.6.5)
Requires-Dist: torchvision (==0.12.0)
Requires-Dist: xlrd (>=0.9.2)
Requires-Dist: xlsxwriter
